README.md
setup.py
example_pkg/__init__.py
example_pkg_conmeo.egg-info/PKG-INFO
example_pkg_conmeo.egg-info/SOURCES.txt
example_pkg_conmeo.egg-info/dependency_links.txt
example_pkg_conmeo.egg-info/top_level.txt