Metadata-Version: 2.1
Name: example-pkg-conmeo
Version: 0.0.1
Summary: A small con meo package
Home-page: https://github.com/pypa/sampleproject
Author: Author ConMeo
Author-email: author@conmeo.com
License: UNKNOWN
Platform: UNKNOWN
Classifier: Programming Language :: Python :: 3
Classifier: License :: OSI Approved :: MIT License
Classifier: Operating System :: OS Independent
Requires-Python: >=3.6
